{
  "$schema": "https://developer.microsoft.com/json-schemas/fabric/item/report/definition/visualContainer/2.5.0/schema.json",
  "name": "v_stale_card_files",
  "position": {"x": 20, "y": 20, "z": 100, "height": 100, "width": 290, "tabOrder": 100},
  "visual": {
    "visualType": "card",
    "query": {
      "queryState": {
        "Values": {
          "projections": [{
            "field": {
              "Measure": {
                "Expression": {"SourceRef": {"Entity": "_Measures"}},
                "Property": "Stale Files"
              }
            },
            "queryRef": "_Measures.Stale Files"
          }]
        }
      }
    },
    "objects": {
      "categoryLabels": [{"properties": {"show": {"expr": {"Literal": {"Value": "false"}}}}}]
    },
    "visualContainerObjects": {
      "title": [{"properties": {
        "show": {"expr": {"Literal": {"Value": "true"}}},
        "text": {"expr": {"Literal": {"Value": "'Stale Files (>180d)'"}}}
      }}]
    }
  }
}
